tree_sitter_c/__init__.py
tree_sitter_c/__init__.pyi
tree_sitter_c/_binding.abi3.so
tree_sitter_c/binding.c
tree_sitter_c/py.typed
tree_sitter_c/queries/highlights.scm
tree_sitter_c/queries/tags.scm
tree_sitter_c-0.24.1.dist-info/METADATA
tree_sitter_c-0.24.1.dist-info/WHEEL
tree_sitter_c-0.24.1.dist-info/top_level.txt
tree_sitter_c-0.24.1.dist-info/RECORD
tree_sitter_c-0.24.1.dist-info/licenses/LICENSE
