Metadata-Version: 2.4
Name: tree-sitter-c
Version: 0.24.1
Summary: C grammar for tree-sitter
Author-email: Max Brunsfeld <maxbrunsfeld@gmail.com>, Amaan Qureshi <amaanq12@gmail.com>
License: MIT
Project-URL: Homepage, https://github.com/tree-sitter/tree-sitter-c
Keywords: incremental,parsing,tree-sitter,c
Classifier: Intended Audience :: Developers
Classifier: License :: OSI Approved :: MIT License
Classifier: Topic :: Software Development :: Compilers
Classifier: Topic :: Text Processing :: Linguistic
Classifier: Typing :: Typed
Requires-Python: >=3.10
License-File: LICENSE
Provides-Extra: core
Requires-Dist: tree-sitter~=0.24; extra == "core"
Dynamic: license-file
